neura_sdk/__init__.py
neura_sdk/client.py
neura_sdk-0.2.0.dist-info/licenses/LICENSE
neura_sdk-0.2.0.dist-info/METADATA
neura_sdk-0.2.0.dist-info/WHEEL
neura_sdk-0.2.0.dist-info/top_level.txt
neura_sdk-0.2.0.dist-info/RECORD
