Metadata-Version: 2.4
Name: neura_sdk
Version: 0.2.0
Summary: Neura Control SDK for Python
Author-email: NEURA AI <engineering@neura-os.com>
License: Apache-2.0
Project-URL: Homepage, https://neura-os.com
Project-URL: Bug Tracker, https://github.com/neura-os/neura-sdk/issues
Classifier: Programming Language :: Python :: 3
Classifier: License :: OSI Approved :: Apache Software License
Classifier: Operating System :: OS Independent
Requires-Python: >=3.7
License-File: LICENSE
Requires-Dist: requests>=2.25.0
Dynamic: license-file
